Workbook

Sheet BUY
B1: Min Est Qty | C1: Min Sell Price | D1: Max BSR | E1: Total Profit | F1: Overall ROI | G1: Total Sales | K1: Max Order Qty | L1: Days of Stock | M1: Supplier Commission | N1: Discount | O1: Total Units | P1: Total Amount | Q1: AMZ Less | R1: Case Pk Default | S1: Min ROI | T1: 25% | U1: 20% | X1: Max BSR 30 | Y1: Max Chng 30 | Z1: Max BSR 90 | AA1: Max Chng 90 | AB1: Min Est Qty | AC1: Var Opp | AD1: Max AMZ OOS | AE1: Max Bbox OOS
B2: 30 | C2: 9 | D2: 100000 | E2: =SUM(F4:F204) | F2: 0 | G2: =SUM(P4:P204) | K2: 240 | L2: 60 | M2: 0 | N2: 0 | O2: =SUM(O4:O204) | P2: =SUM(P4:P204) | Q2: 0.05 | R2: 12 | S2: Min Profit | T2: 1.5 | U2: 2 | X2: 125000 | Y2: 0.5 | Z2: 150000 | AA2: 0.75 | AB2: 300 | AC2: 0.07 | AD2: 0.35 | AE2: 0.5
A3: ASIN | B3: AMZ Title | C3: Est. Qty | D3: Sell Price | E3: Current BSR | F3: Profit | G3: ROI | H3: Sales Opp. | I3: Suggested Pk | J3: Pack Qty | K3: Odr Qty (Pk) | L3: Item Code | M3: Description | N3: Cost | O3: Order Qty (Unit) | P3: Order Amount | Q3: Var Weight | R3: Case Pack | S3: Offers 90d | T3: ROI/Profit | U3: Visible | V3: Var. Opp. | W3: Use Qty | X3: BSR 30 Avg | Y3: % Chng30 | Z3: BSR 90 Avg | AA3: % Chng90 | AB3: Avail. Qty | AC3: AMZ Boss | AD3: AMZ OOS | AE3: Bbox OOS | AF3: Brand | AG3: Keepa Link | AH3: AMZ Product Page | AI3: Check Gated in SC | AJ3: Extra1 | AK3: Extra2 | AL3: Extra3
D4: =IFERROR(VLOOKUP(A4, RESEARCH!$A$4:$AS$5000, 14, FALSE), 0) | E4: =IFERROR(VLOOKUP(A4, RESEARCH!$A$4:$AS$5000, 8, FALSE), 0) | F4: =D4-N4 | G4: =IF(N4=0,0,F4/N4) | H4: =IFERROR(VLOOKUP(A4, RESEARCH!$A$4:$AS$5000, 9, FALSE), 0) | L4: =IF(H4=0, 999, AB4/(H4/30)) | N4: =IFERROR(VLOOKUP(A4, RESEARCH!$A$4:$AS$5000, 13, FALSE), 0) | O4: =MAX(0, ($L$2 * (H4/30)) - AB4) | P4: =N4*O4 | X4: =IFERROR(VLOOKUP(A4, KEEPA!$A$4:$AW$5000, 26, FALSE), 0) | Y4: =IF(X4=0,0,(X4-E4)/X4) | Z4: =IFERROR(VLOOKUP(A4, KEEPA!$A$4:$AW$5000, 28, FALSE), 0) | AA4: =IF(Z4=0,0,(Z4-E4)/Z4)
D5: =IFERROR(VLOOKUP(A5, RESEARCH!$A$4:$AS$5000, 14, FALSE), 0) | E5: =IFERROR(VLOOKUP(A5, RESEARCH!$A$4:$AS$5000, 8, FALSE), 0) | F5: =D5-N5 | G5: =IF(N5=0,0,F5/N5) | H5: =IFERROR(VLOOKUP(A5, RESEARCH!$A$4:$AS$5000, 9, FALSE), 0) | L5: =IF(H5=0, 999, AB5/(H5/30)) | N5: =IFERROR(VLOOKUP(A5, RESEARCH!$A$4:$AS$5000, 13, FALSE), 0) | O5: =MAX(0, ($L$2 * (H5/30)) - AB5) | P5: =N5*O5 | X5: =IFERROR(VLOOKUP(A5, KEEPA!$A$4:$AW$5000, 26, FALSE), 0) | Y5: =IF(X5=0,0,(X5-E5)/X5) | Z5: =IFERROR(VLOOKUP(A5, KEEPA!$A$4:$AW$5000, 28, FALSE), 0) | AA5: =IF(Z5=0,0,(Z5-E5)/Z5)
D6: =IFERROR(VLOOKUP(A6, RESEARCH!$A$4:$AS$5000, 14, FALSE), 0) | E6: =IFERROR(VLOOKUP(A6, RESEARCH!$A$4:$AS$5000, 8, FALSE), 0) | F6: =D6-N6 | G6: =IF(N6=0,0,F6/N6) | H6: =IFERROR(VLOOKUP(A6, RESEARCH!$A$4:$AS$5000, 9, FALSE), 0) | L6: =IF(H6=0, 999, AB6/(H6/30)) | N6: =IFERROR(VLOOKUP(A6, RESEARCH!$A$4:$AS$5000, 13, FALSE), 0) | O6: =MAX(0, ($L$2 * (H6/30)) - AB6) | P6: =N6*O6 | X6: =IFERROR(VLOOKUP(A6, KEEPA!$A$4:$AW$5000, 26, FALSE), 0) | Y6: =IF(X6=0,0,(X6-E6)/X6) | Z6: =IFERROR(VLOOKUP(A6, KEEPA!$A$4:$AW$5000, 28, FALSE), 0) | AA6: =IF(Z6=0,0,(Z6-E6)/Z6)
D7: =IFERROR(VLOOKUP(A7, RESEARCH!$A$4:$AS$5000, 14, FALSE), 0) | E7: =IFERROR(VLOOKUP(A7, RESEARCH!$A$4:$AS$5000, 8, FALSE), 0) | F7: =D7-N7 | G7: =IF(N7=0,0,F7/N7) | H7: =IFERROR(VLOOKUP(A7, RESEARCH!$A$4:$AS$5000, 9, FALSE), 0) | L7: =IF(H7=0, 999, AB7/(H7/30)) | N7: =IFERROR(VLOOKUP(A7, RESEARCH!$A$4:$AS$5000, 13, FALSE), 0) | O7: =MAX(0, ($L$2 * (H7/30)) - AB7) | P7: =N7*O7 | X7: =IFERROR(VLOOKUP(A7, KEEPA!$A$4:$AW$5000, 26, FALSE), 0) | Y7: =IF(X7=0,0,(X7-E7)/X7) | Z7: =IFERROR(VLOOKUP(A7, KEEPA!$A$4:$AW$5000, 28, FALSE), 0) | AA7: =IF(Z7=0,0,(Z7-E7)/Z7)
D8: =IFERROR(VLOOKUP(A8, RESEARCH!$A$4:$AS$5000, 14, FALSE), 0) | E8: =IFERROR(VLOOKUP(A8, RESEARCH!$A$4:$AS$5000, 8, FALSE), 0) | F8: =D8-N8 | G8: =IF(N8=0,0,F8/N8) | H8: =IFERROR(VLOOKUP(A8, RESEARCH!$A$4:$AS$5000, 9, FALSE), 0) | L8: =IF(H8=0, 999, AB8/(H8/30)) | N8: =IFERROR(VLOOKUP(A8, RESEARCH!$A$4:$AS$5000, 13, FALSE), 0) | O8: =MAX(0, ($L$2 * (H8/30)) - AB8) | P8: =N8*O8 | X8: =IFERROR(VLOOKUP(A8, KEEPA!$A$4:$AW$5000, 26, FALSE), 0) | Y8: =IF(X8=0,0,(X8-E8)/X8) | Z8: =IFERROR(VLOOKUP(A8, KEEPA!$A$4:$AW$5000, 28, FALSE), 0) | AA8: =IF(Z8=0,0,(Z8-E8)/Z8)
D9: =IFERROR(VLOOKUP(A9, RESEARCH!$A$4:$AS$5000, 14, FALSE), 0) | E9: =IFERROR(VLOOKUP(A9, RESEARCH!$A$4:$AS$5000, 8, FALSE), 0) | F9: =D9-N9 | G9: =IF(N9=0,0,F9/N9) | H9: =IFERROR(VLOOKUP(A9, RESEARCH!$A$4:$AS$5000, 9, FALSE), 0) | L9: =IF(H9=0, 999, AB9/(H9/30)) | N9: =IFERROR(VLOOKUP(A9, RESEARCH!$A$4:$AS$5000, 13, FALSE), 0) | O9: =MAX(0, ($L$2 * (H9/30)) - AB9) | P9: =N9*O9 | X9: =IFERROR(VLOOKUP(A9, KEEPA!$A$4:$AW$5000, 26, FALSE), 0) | Y9: =IF(X9=0,0,(X9-E9)/X9) | Z9: =IFERROR(VLOOKUP(A9, KEEPA!$A$4:$AW$5000, 28, FALSE), 0) | AA9: =IF(Z9=0,0,(Z9-E9)/Z9)
D10: =IFERROR(VLOOKUP(A10, RESEARCH!$A$4:$AS$5000, 14, FALSE), 0) | E10: =IFERROR(VLOOKUP(A10, RESEARCH!$A$4:$AS$5000, 8, FALSE), 0) | F10: =D10-N10 | G10: =IF(N10=0,0,F10/N10) | H10: =IFERROR(VLOOKUP(A10, RESEARCH!$A$4:$AS$5000, 9, FALSE), 0) | L10: =IF(H10=0, 999, AB10/(H10/30)) | N10: =IFERROR(VLOOKUP(A10, RESEARCH!$A$4:$AS$5000, 13, FALSE), 0) | O10: =MAX(0, ($L$2 * (H10/30)) - AB10) | P10: =N10*O10 | X10: =IFERROR(VLOOKUP(A10, KEEPA!$A$4:$AW$5000, 26, FALSE), 0) | Y10: =IF(X10=0,0,(X10-E10)/X10) | Z10: =IFERROR(VLOOKUP(A10, KEEPA!$A$4:$AW$5000, 28, FALSE), 0) | AA10: =IF(Z10=0,0,(Z10-E10)/Z10)
D11: =IFERROR(VLOOKUP(A11, RESEARCH!$A$4:$AS$5000, 14, FALSE), 0) | E11: =IFERROR(VLOOKUP(A11, RESEARCH!$A$4:$AS$5000, 8, FALSE), 0) | F11: =D11-N11 | G11: =IF(N11=0,0,F11/N11) | H11: =IFERROR(VLOOKUP(A11, RESEARCH!$A$4:$AS$5000, 9, FALSE), 0) | L11: =IF(H11=0, 999, AB11/(H11/30)) | N11: =IFERROR(VLOOKUP(A11, RESEARCH!$A$4:$AS$5000, 13, FALSE), 0) | O11: =MAX(0, ($L$2 * (H11/30)) - AB11) | P11: =N11*O11 | X11: =IFERROR(VLOOKUP(A11, KEEPA!$A$4:$AW$5000, 26, FALSE), 0) | Y11: =IF(X11=0,0,(X11-E11)/X11) | Z11: =IFERROR(VLOOKUP(A11, KEEPA!$A$4:$AW$5000, 28, FALSE), 0) | AA11: =IF(Z11=0,0,(Z11-E11)/Z11)
D12: =IFERROR(VLOOKUP(A12, RESEARCH!$A$4:$AS$5000, 14, FALSE), 0) | E12: =IFERROR(VLOOKUP(A12, RESEARCH!$A$4:$AS$5000, 8, FALSE), 0) | F12: =D12-N12 | G12: =IF(N12=0,0,F12/N12) | H12: =IFERROR(VLOOKUP(A12, RESEARCH!$A$4:$AS$5000, 9, FALSE), 0) | L12: =IF(H12=0, 999, AB12/(H12/30)) | N12: =IFERROR(VLOOKUP(A12, RESEARCH!$A$4:$AS$5000, 13, FALSE), 0) | O12: =MAX(0, ($L$2 * (H12/30)) - AB12) | P12: =N12*O12 | X12: =IFERROR(VLOOKUP(A12, KEEPA!$A$4:$AW$5000, 26, FALSE), 0) | Y12: =IF(X12=0,0,(X12-E12)/X12) | Z12: =IFERROR(VLOOKUP(A12, KEEPA!$A$4:$AW$5000, 28, FALSE), 0) | AA12: =IF(Z12=0,0,(Z12-E12)/Z12)
D13: =IFERROR(VLOOKUP(A13, RESEARCH!$A$4:$AS$5000, 14, FALSE), 0) | E13: =IFERROR(VLOOKUP(A13, RESEARCH!$A$4:$AS$5000, 8, FALSE), 0) | F13: =D13-N13 | G13: =IF(N13=0,0,F13/N13) | H13: =IFERROR(VLOOKUP(A13, RESEARCH!$A$4:$AS$5000, 9, FALSE), 0) | L13: =IF(H13=0, 999, AB13/(H13/30)) | N13: =IFERROR(VLOOKUP(A13, RESEARCH!$A$4:$AS$5000, 13, FALSE), 0) | O13: =MAX(0, ($L$2 * (H13/30)) - AB13) | P13: =N13*O13 | X13: =IFERROR(VLOOKUP(A13, KEEPA!$A$4:$AW$5000, 26, FALSE), 0) | Y13: =IF(X13=0,0,(X13-E13)/X13) | Z13: =IFERROR(VLOOKUP(A13, KEEPA!$A$4:$AW$5000, 28, FALSE), 0) | AA13: =IF(Z13=0,0,(Z13-E13)/Z13)
D14: =IFERROR(VLOOKUP(A14, RESEARCH!$A$4:$AS$5000, 14, FALSE), 0) | E14: =IFERROR(VLOOKUP(A14, RESEARCH!$A$4:$AS$5000, 8, FALSE), 0) | F14: =D14-N14 | G14: =IF(N14=0,0,F14/N14) | H14: =IFERROR(VLOOKUP(A14, RESEARCH!$A$4:$AS$5000, 9, FALSE), 0) | L14: =IF(H14=0, 999, AB14/(H14/30)) | N14: =IFERROR(VLOOKUP(A14, RESEARCH!$A$4:$AS$5000, 13, FALSE), 0) | O14: =MAX(0, ($L$2 * (H14/30)) - AB14) | P14: =N14*O14 | X14: =IFERROR(VLOOKUP(A14, KEEPA!$A$4:$AW$5000, 26, FALSE), 0) | Y14: =IF(X14=0,0,(X14-E14)/X14) | Z14: =IFERROR(VLOOKUP(A14, KEEPA!$A$4:$AW$5000, 28, FALSE), 0) | AA14: =IF(Z14=0,0,(Z14-E14)/Z14)
D15: =IFERROR(VLOOKUP(A15, RESEARCH!$A$4:$AS$5000, 14, FALSE), 0) | E15: =IFERROR(VLOOKUP(A15, RESEARCH!$A$4:$AS$5000, 8, FALSE), 0) | F15: =D15-N15 | G15: =IF(N15=0,0,F15/N15) | H15: =IFERROR(VLOOKUP(A15, RESEARCH!$A$4:$AS$5000, 9, FALSE), 0) | L15: =IF(H15=0, 999, AB15/(H15/30)) | N15: =IFERROR(VLOOKUP(A15, RESEARCH!$A$4:$AS$5000, 13, FALSE), 0) | O15: =MAX(0, ($L$2 * (H15/30)) - AB15) | P15: =N15*O15 | X15: =IFERROR(VLOOKUP(A15, KEEPA!$A$4:$AW$5000, 26, FALSE), 0) | Y15: =IF(X15=0,0,(X15-E15)/X15) | Z15: =IFERROR(VLOOKUP(A15, KEEPA!$A$4:$AW$5000, 28, FALSE), 0) | AA15: =IF(Z15=0,0,(Z15-E15)/Z15)
... D203: =IFERROR(VLOOKUP(A203, RESEARCH!$A$4:$AS$5000, 14, FALSE), 0) | E203: =IFERROR(VLOOKUP(A203, RESEARCH!$A$4:$AS$5000, 8, FALSE), 0) | F203: =D203-N203 | G203: =IF(N203=0,0,F203/N203) | H203: =IFERROR(VLOOKUP(A203, RESEARCH!$A$4:$AS$5000, 9, FALSE), 0) | L203: =IF(H203=0, 999, AB203/(H203/30)) | N203: =IFERROR(VLOOKUP(A203, RESEARCH!$A$4:$AS$5000, 13, FALSE), 0) | O203: =MAX(0, ($L$2 * (H203/30)) - AB203) | P203: =N203*O203 | X203: =IFERROR(VLOOKUP(A203, KEEPA!$A$4:$AW$5000, 26, FALSE), 0) | Y203: =IF(X203=0,0,(X203-E203)/X203) | Z203: =IFERROR(VLOOKUP(A203, KEEPA!$A$4:$AW$5000, 28, FALSE), 0) | AA203: =IF(Z203=0,0,(Z203-E203)/Z203)

Sheet RESEARCH
A1: Total Items | B1: 4389 | C1: Matches Found on AMZ | D1: 4389 | E1: Not Found on AMZ | F1: 0
A3: ASIN | B3: Product ID | C3: Title | D3: Package Quantity | E3: Brand | F3: Product Group | G3: Total Offers | H3: Sales Rank | I3: Estimated Number of Sales | J3: Profit | K3: Margin | L3: ROI | M3: Purchase Price | N3: Sell Price | O3: Buy Box Landed | P3: Seller Proceeds | Q3: Low New Fba Price | R3: Low New Mfn Price | S3: Referral Fee | T3: Variable Closing Fee | U3: Fulfillment Subtotal | V3: Cost Sub Total | W3: VAT % | X3: VAT $ | Y3: Inbound Shipping Estimate | Z3: Package Weight | AA3: Package Height | AB3: Package Length | AC3: Package Width | AD3: New FBA Num Offers | AE3: New MFN Num Offers | AF3: Keepa | AG3: CamelCC | AH3: Size | AI3: Last Run | AJ3: Item Number | AK3: PRODUCT | AL3: SKU # | AM3: Size(1) | AN3: Case Pk | AO3: Salon price / each | AP3: Salon price / case | AQ3: QTY | AR3: YOUR TOTAL COST | AS3: CASE COUNT

Sheet ORDER
A1: Item Code | B1: Description | C1: Unit Cost | D1: Order Qty | E1: Total Amount

Sheet KEEPA
B1: 30 wt | C1: 90 wt | D1: 180 wt | F1: AMZ Less:
B2: 1 | C2: 3 | D2: 1 | F2: 0.05
A3: ASIN | B3: Baseline | C3: BB Avg | D3: AMZ Avg | E3: wtd avg | F3: Variations | G3: Review Wt | H3: Confidence | I3: ASIN_SRC | J3: Title | K3: Buy Box: Current | L3: Buy Box: 30 days avg. | M3: Buy Box: 30 days drop % | N3: Buy Box: 90 days avg. | O3: Buy Box: 90 days drop % | P3: Buy Box: 180 days avg. | Q3: Buy Box Seller | R3: Amazon: Current | S3: Amazon: 30 days avg. | T3: Amazon: 30 days drop % | U3: Amazon: 90 days avg. | V3: Amazon: 90 days drop % | W3: Amazon: 180 days avg. | X3: Amazon out of stock percentage: 90 days OOS % | Y3: Sales Rank: Current | Z3: Sales Rank: 30 days avg. | AA3: Sales Rank: 30 days drop % | AB3: Sales Rank: 90 days avg. | AC3: Sales Rank: 90 days drop % | AD3: Sales Rank: 180 days avg. | AE3: Count of retrieved live offers: New, FBA | AF3: Count of retrieved live offers: New, FBM | AG3: New Offer Count: Current | AH3: New Offer Count: 90 days avg. | AI3: New, 3rd Party FBA: 30 days avg. | AJ3: New, 3rd Party FBA: 90 days avg. | AK3: New, 3rd Party FBA: 180 days avg. | AL3: Variation ASINs | AM3: Parent ASIN | AN3: Reviews: Reviews - Format Specific | AO3: Variation Attributes | AP3: Reviews: Review Count | AQ3: Model | AR3: Number of Items | AS3: Categories: Root | AT3: FBA Fees: | AU3: Referral Fee % | AV3: Buy Box out of stock percentage: 90 days OOS %
E4: =IFERROR(=(Z4*KEEPA!$B$2 + AB4*KEEPA!$C$2 + AD4*KEEPA!$D$2) / (KEEPA!$B$2 + KEEPA!$C$2 + KEEPA!$D$2), 0)
E5: =IFERROR(=(Z5*KEEPA!$B$2 + AB5*KEEPA!$C$2 + AD5*KEEPA!$D$2) / (KEEPA!$B$2 + KEEPA!$C$2 + KEEPA!$D$2), 0)
E6: =IFERROR(=(Z6*KEEPA!$B$2 + AB6*KEEPA!$C$2 + AD6*KEEPA!$D$2) / (KEEPA!$B$2 + KEEPA!$C$2 + KEEPA!$D$2), 0)
E7: =IFERROR(=(Z7*KEEPA!$B$2 + AB7*KEEPA!$C$2 + AD7*KEEPA!$D$2) / (KEEPA!$B$2 + KEEPA!$C$2 + KEEPA!$D$2), 0)
E8: =IFERROR(=(Z8*KEEPA!$B$2 + AB8*KEEPA!$C$2 + AD8*KEEPA!$D$2) / (KEEPA!$B$2 + KEEPA!$C$2 + KEEPA!$D$2), 0)
E9: =IFERROR(=(Z9*KEEPA!$B$2 + AB9*KEEPA!$C$2 + AD9*KEEPA!$D$2) / (KEEPA!$B$2 + KEEPA!$C$2 + KEEPA!$D$2), 0)
E10: =IFERROR(=(Z10*KEEPA!$B$2 + AB10*KEEPA!$C$2 + AD10*KEEPA!$D$2) / (KEEPA!$B$2 + KEEPA!$C$2 + KEEPA!$D$2), 0)
E11: =IFERROR(=(Z11*KEEPA!$B$2 + AB11*KEEPA!$C$2 + AD11*KEEPA!$D$2) / (KEEPA!$B$2 + KEEPA!$C$2 + KEEPA!$D$2), 0)
E12: =IFERROR(=(Z12*KEEPA!$B$2 + AB12*KEEPA!$C$2 + AD12*KEEPA!$D$2) / (KEEPA!$B$2 + KEEPA!$C$2 + KEEPA!$D$2), 0)
E13: =IFERROR(=(Z13*KEEPA!$B$2 + AB13*KEEPA!$C$2 + AD13*KEEPA!$D$2) / (KEEPA!$B$2 + KEEPA!$C$2 + KEEPA!$D$2), 0)
E14: =IFERROR(=(Z14*KEEPA!$B$2 + AB14*KEEPA!$C$2 + AD14*KEEPA!$D$2) / (KEEPA!$B$2 + KEEPA!$C$2 + KEEPA!$D$2), 0)
E15: =IFERROR(=(Z15*KEEPA!$B$2 + AB15*KEEPA!$C$2 + AD15*KEEPA!$D$2) / (KEEPA!$B$2 + KEEPA!$C$2 + KEEPA!$D$2), 0)
... E203: =IFERROR(=(Z203*KEEPA!$B$2 + AB203*KEEPA!$C$2 + AD203*KEEPA!$D$2) / (KEEPA!$B$2 + KEEPA!$C$2 + KEEPA!$D$2), 0)

Sheet IP Qty
A1: Image | B1: Name | C1: SKU | D1: Barcode | E1: Cost Price | F1: Price | G1: Replenishment | H1: To Order | I1: Stock | J1: On Order | K1: Sales | L1: Adjusted Sales Velocity/mo | M1: Lead Time | N1: Days of Stock | O1: Vendors | P1: Brand | Q1: AVG Retail Price | R1: Replenishable | S1: In Buy Sheet?
